liteblue/__init__.py
liteblue/authentication.py
liteblue/config.py
liteblue/connection.py
liteblue/describe.py
liteblue/moo.py
liteblue/server.py
liteblue/user.py
liteblue/worker.py
liteblue/apps/__init__.py
liteblue/apps/cfg.py
liteblue/apps/db.py
liteblue/apps/docker.py
liteblue/apps/run.py
liteblue/apps/utils.py
liteblue/apps/simple/__init__.py.tmpl
liteblue/apps/simple/config.py.tmpl
liteblue/apps/simple/main.py.tmpl
liteblue/apps/simple/procedures.py.tmpl
liteblue/apps/simple/tables.py.tmpl
liteblue/apps/simple/scripts/README
liteblue/apps/simple/scripts/env.py.tmpl
liteblue/apps/simple/scripts/script.py.mako.tmpl
liteblue/apps/static/app.js
liteblue/apps/static/es_rpc.js
liteblue/apps/static/favicon.ico
liteblue/apps/static/index.html
liteblue/apps/static/site.css
liteblue/apps/static/ws_rpc.js
liteblue/handlers/__init__.py
liteblue/handlers/broadcast_mixin.py
liteblue/handlers/broadcaster.py
liteblue/handlers/context.py
liteblue/handlers/event_source.py
liteblue/handlers/json_rpc_mixin.py
liteblue/handlers/json_utils.py
liteblue/handlers/login.html
liteblue/handlers/login_handler.py
liteblue/handlers/rpc_handler.py
liteblue/handlers/rpc_websocket.py
liteblue/handlers/static_file_handler.py
liteblue/handlers/user_mixin.py
liteblue-0.0.15.dist-info/LICENSE
liteblue-0.0.15.dist-info/METADATA
liteblue-0.0.15.dist-info/WHEEL
liteblue-0.0.15.dist-info/entry_points.txt
liteblue-0.0.15.dist-info/top_level.txt
liteblue-0.0.15.dist-info/RECORD
