Metadata-Version: 2.1
Name: liteblue
Version: 0.0.15
Summary: UNKNOWN
Home-page: https://github.com/blueshed/liteblue/
License: UNKNOWN
Platform: UNKNOWN
Classifier: Programming Language :: Python :: 3
Classifier: License :: OSI Approved :: MIT License
Classifier: Operating System :: OS Independent
Requires-Dist: invoke
Requires-Dist: alembic
Requires-Dist: sqlalchemy
Requires-Dist: pymysql
Requires-Dist: aioredis
Requires-Dist: tornado
